rika_ntrip_client/__init__.py
rika_ntrip_client/rika_ntrip_client.py
rtkpoint/__init__.py
rtkpoint/rtkpoint.py
rtkpoint-0.1.1.dist-info/METADATA
rtkpoint-0.1.1.dist-info/WHEEL
rtkpoint-0.1.1.dist-info/top_level.txt
rtkpoint-0.1.1.dist-info/RECORD
