Metadata-Version: 2.1
Name: rtkpoint
Version: 0.1.1
Summary: A Python library for interacting with RTKPOINT, a NTRIP caster
Author: Rika Inc.
Author-email: developer@rtkpoint.com
Classifier: Programming Language :: Python :: 3
Classifier: License :: OSI Approved :: MIT License
Classifier: Operating System :: OS Independent
Requires-Python: >=3.6
Requires-Dist: pyrtcm
